glassmath/__init__.py
glassmath/calcplus.py
glassmath-0.0.0.dist-info/LICENSE
glassmath-0.0.0.dist-info/METADATA
glassmath-0.0.0.dist-info/WHEEL
glassmath-0.0.0.dist-info/top_level.txt
glassmath-0.0.0.dist-info/RECORD
