Metadata-Version: 2.1
Name: glassmath
Version: 0.0.0
Summary: [IN BETA TESTING]More advanced version of the math module. Protected by Apache 2.0 License.
Author: PyModuleDev
License-File: LICENSE
